extension_helpers/__init__.py
extension_helpers/_openmp_helpers.py
extension_helpers/_setup_helpers.py
extension_helpers/_utils.py
extension_helpers/conftest.py
extension_helpers/version.py
extension_helpers/src/compiler.c
extension_helpers/tests/__init__.py
extension_helpers/tests/py311_backports.py
extension_helpers/tests/test_openmp_helpers.py
extension_helpers/tests/test_setup_helpers.py
extension_helpers/tests/test_utils.py
extension_helpers-1.3.0.dist-info/licenses/LICENSE.rst
extension_helpers-1.3.0.dist-info/METADATA
extension_helpers-1.3.0.dist-info/WHEEL
extension_helpers-1.3.0.dist-info/entry_points.txt
extension_helpers-1.3.0.dist-info/top_level.txt
extension_helpers-1.3.0.dist-info/RECORD
