Metadata-Version: 2.4
Name: extension-helpers
Version: 1.3.0
Summary: Utilities for building and installing packages with compiled extensions
Author-email: The Astropy Developers <astropy.team@gmail.com>
License: BSD 3-Clause License
Project-URL: Homepage, https://github.com/astropy/extension-helpers
Classifier: Development Status :: 5 - Production/Stable
Classifier: Intended Audience :: Developers
Classifier: Framework :: Setuptools Plugin
Classifier: License :: OSI Approved :: BSD License
Classifier: Operating System :: OS Independent
Classifier: Programming Language :: Python
Classifier: Programming Language :: Python :: 3
Classifier: Topic :: Software Development :: Build Tools
Classifier: Topic :: Software Development :: Libraries :: Python Modules
Classifier: Topic :: System :: Archiving :: Packaging
Provides: extension_helpers
Requires-Python: >=3.10
License-File: LICENSE.rst
Requires-Dist: setuptools>=64
Requires-Dist: tomli>=1.0.0; python_version < "3.11"
Provides-Extra: test
Requires-Dist: wheel; extra == "test"
Requires-Dist: pytest; extra == "test"
Requires-Dist: pytest-cov; extra == "test"
Requires-Dist: cython; extra == "test"
Requires-Dist: build; extra == "test"
Provides-Extra: docs
Requires-Dist: sphinx; extra == "docs"
Requires-Dist: sphinx-automodapi; extra == "docs"
Dynamic: license-file
